relevanceai/__init__.py
relevanceai/_request.py
relevanceai/auth.py
relevanceai/chain.py
relevanceai/datasets.py
relevanceai/env.py
relevanceai/params.py
relevanceai/steps/__init__.py
relevanceai/steps/_base.py
relevanceai/steps/api_call.py
relevanceai/steps/execute_javascript.py
relevanceai/steps/prompt_completion.py
relevanceai/steps/redis_vector_search.py
relevanceai/steps/vector_search.py
relevanceai_chains-1.0.1.dist-info/LICENSE
relevanceai_chains-1.0.1.dist-info/METADATA
relevanceai_chains-1.0.1.dist-info/WHEEL
relevanceai_chains-1.0.1.dist-info/top_level.txt
relevanceai_chains-1.0.1.dist-info/RECORD
