Metadata-Version: 2.1
Name: relevanceai-chains
Version: 1.0.1
Home-page: https://relevanceai.com/
Author: Relevance AI
Author-email: jacky@relevanceai.com
License-File: LICENSE
Requires-Dist: requests
